sessyoin/__init__.py
sessyoin/client.py
sessyoin/errors.py
sessyoin/http.py
sessyoin/models.py
sessyoin-0.0.1.dist-info/LICENSE
sessyoin-0.0.1.dist-info/METADATA
sessyoin-0.0.1.dist-info/WHEEL
sessyoin-0.0.1.dist-info/top_level.txt
sessyoin-0.0.1.dist-info/RECORD
