Metadata-Version: 2.1
Name: sessyoin
Version: 0.0.1
Summary: Advanced cosplay wrapper: hq, wholesome, crot, huge data, and no key requirements.
Home-page: https://github.com/sinkaroid/sessyoinAsync.py
Author: sinkaroid
License: MIT
Project-URL: Issue Tracker, https://github.com/sinkaroid/sessyoinAsync/issues
Project-URL: Source Code, https://github.com/sinkaroid/sessyoinAsync
Platform: UNKNOWN
Classifier: Development Status :: 2 - Pre-Alpha
Classifier: Framework :: AsyncIO
Classifier: Intended Audience :: Developers
Classifier: License :: OSI Approved :: MIT License
Classifier: Natural Language :: English
Classifier: Operating System :: OS Independent
Classifier: Programming Language :: Python :: 3.8
Classifier: Programming Language :: Python :: 3.9
Classifier: Topic :: Internet
Classifier: Topic :: Software Development :: Libraries
Classifier: Topic :: Software Development :: Libraries :: Python Modules
Classifier: Topic :: Utilities
Requires-Python: >=3.8
Requires-Dist: aiohttp (<3.7.3,>=3.6.2)
